django_add_default_value/__init__.py
django_add_default_value/add_default_value.py
django_add_default_value-0.10.0.dist-info/LICENSE.txt
django_add_default_value-0.10.0.dist-info/METADATA
django_add_default_value-0.10.0.dist-info/WHEEL
django_add_default_value-0.10.0.dist-info/top_level.txt
django_add_default_value-0.10.0.dist-info/RECORD
